sia_storage
