Metadata-Version: 2.1
Name: sia-storage-access
Version: 1.0.0
Summary: Sia Storage Access Layer
Home-page: https://github.com/sumalata23dsa/SIA_API_BACKEND
Author: Data Stride Analytics
License: proprietary
Requires-Python: >=3.8.0
License-File: LICENSE
Requires-Dist: azure-data-tables==12.6.0
Requires-Dist: azure-storage-blob==12.24.0
Requires-Dist: azure-storage-file-datalake==12.18.0
